draw_real_time/__init__.py
draw_real_time/canvas.py
draw_real_time-0.1.2.dist-info/LICENSE
draw_real_time-0.1.2.dist-info/METADATA
draw_real_time-0.1.2.dist-info/WHEEL
draw_real_time-0.1.2.dist-info/top_level.txt
draw_real_time-0.1.2.dist-info/RECORD
